_subprocessww.pyd
subprocessww.py
subprocessww-0.1.dist-info/DESCRIPTION.rst
subprocessww-0.1.dist-info/METADATA
subprocessww-0.1.dist-info/RECORD
subprocessww-0.1.dist-info/WHEEL
subprocessww-0.1.dist-info/metadata.json
subprocessww-0.1.dist-info/top_level.txt
